karrio/mappers/ups/__init__.py
karrio/mappers/ups/mapper.py
karrio/mappers/ups/proxy.py
karrio/mappers/ups/settings.py
karrio/plugins/ups/__init__.py
karrio/providers/ups/__init__.py
karrio/providers/ups/document.py
karrio/providers/ups/error.py
karrio/providers/ups/rate.py
karrio/providers/ups/tracking.py
karrio/providers/ups/units.py
karrio/providers/ups/utils.py
karrio/providers/ups/pickup/__init__.py
karrio/providers/ups/pickup/cancel.py
karrio/providers/ups/pickup/create.py
karrio/providers/ups/shipment/__init__.py
karrio/providers/ups/shipment/cancel.py
karrio/providers/ups/shipment/create.py
karrio/schemas/ups/__init__.py
karrio/schemas/ups/document_upload_request.py
karrio/schemas/ups/document_upload_response.py
karrio/schemas/ups/error_response.py
karrio/schemas/ups/pickup_request.py
karrio/schemas/ups/pickup_response.py
karrio/schemas/ups/rating_request.py
karrio/schemas/ups/rating_response.py
karrio/schemas/ups/shipping_cancel_response.py
karrio/schemas/ups/shipping_request.py
karrio/schemas/ups/shipping_response.py
karrio/schemas/ups/tracking_response.py
karrio_ups-2026.1.4.dist-info/METADATA
karrio_ups-2026.1.4.dist-info/WHEEL
karrio_ups-2026.1.4.dist-info/entry_points.txt
karrio_ups-2026.1.4.dist-info/top_level.txt
karrio_ups-2026.1.4.dist-info/RECORD
